valyu/__init__.py
valyu/api.py
valyu/batch_client.py
valyu/deepresearch_client.py
valyu/validation.py
valyu/core/__init__.py
valyu/core/provider.py
valyu/core/types.py
valyu/providers/__init__.py
valyu/providers/anthropic.py
valyu/providers/openai.py
valyu/types/__init__.py
valyu/types/answer.py
valyu/types/contents.py
valyu/types/datasources.py
valyu/types/deepresearch.py
valyu/types/response.py
valyu-2.5.4.dist-info/METADATA
valyu-2.5.4.dist-info/WHEEL
valyu-2.5.4.dist-info/top_level.txt
valyu-2.5.4.dist-info/RECORD
