Metadata-Version: 2.4
Name: valyu
Version: 2.5.4
Summary: Deepsearch API for AI.
Home-page: https://valyu.ai
Author: Valyu
Author-email: contact@valyu.ai
Maintainer: Harvey Yorke
Maintainer-email: harvey@valyu.ai
Classifier: Programming Language :: Python :: 3
Classifier: License :: OSI Approved :: MIT License
Classifier: Operating System :: OS Independent
Requires-Python: >=3.6
Requires-Dist: requests>=2.31.0
Requires-Dist: pydantic>=2.5.0
Requires-Dist: openai>=1.66.0
Requires-Dist: anthropic>=0.46.0
Requires-Dist: python-dotenv>=1.0.0
Dynamic: author
Dynamic: author-email
Dynamic: classifier
Dynamic: description
Dynamic: description-content-type
Dynamic: home-page
Dynamic: maintainer
Dynamic: maintainer-email
Dynamic: requires-dist
Dynamic: requires-python
Dynamic: summary
